pyfortracc/__init__.py
pyfortracc/_version.py
pyfortracc/concat.py
pyfortracc/default_parameters.py
pyfortracc/spatial_conversion.py
pyfortracc/track.py
pyfortracc/cluster_linking/__init__.py
pyfortracc/cluster_linking/board_clusters.py
pyfortracc/cluster_linking/cluster_linking.py
pyfortracc/cluster_linking/max_uid.py
pyfortracc/cluster_linking/merge_trajectory.py
pyfortracc/cluster_linking/new_frame.py
pyfortracc/cluster_linking/refact_inside.py
pyfortracc/features_extraction/__init__.py
pyfortracc/features_extraction/clustering.py
pyfortracc/features_extraction/features_extraction.py
pyfortracc/features_extraction/statistics.py
pyfortracc/forecast/__init__.py
pyfortracc/forecast/forecast.py
pyfortracc/forecast/persistence.py
pyfortracc/plot/__init__.py
pyfortracc/plot/plot.py
pyfortracc/plot/plot_animation.py
pyfortracc/post_processing/__init__.py
pyfortracc/post_processing/add_raster_data.py
pyfortracc/post_processing/duration.py
pyfortracc/post_processing/fortracc_converter.py
pyfortracc/post_processing/spatial_vectors.py
pyfortracc/spatial_conversions/__init__.py
pyfortracc/spatial_conversions/boundaries.py
pyfortracc/spatial_conversions/clusters.py
pyfortracc/spatial_conversions/spatial_conversions.py
pyfortracc/spatial_conversions/trajectories.py
pyfortracc/spatial_conversions/vectorfield.py
pyfortracc/spatial_operations/__init__.py
pyfortracc/spatial_operations/count_inside.py
pyfortracc/spatial_operations/edge_clusters.py
pyfortracc/spatial_operations/expansion.py
pyfortracc/spatial_operations/overlay.py
pyfortracc/spatial_operations/spatial_class.py
pyfortracc/spatial_operations/spatial_operations.py
pyfortracc/spatial_operations/trajectory.py
pyfortracc/spatial_operations/validation.py
pyfortracc/utilities/__init__.py
pyfortracc/utilities/bubble_simulation.py
pyfortracc/utilities/conversions.py
pyfortracc/utilities/math_utils.py
pyfortracc/utilities/transform.py
pyfortracc/utilities/utils.py
pyfortracc/vector_methods/__init__.py
pyfortracc-1.2.5.dist-info/licenses/LICENSE
pyfortracc-1.2.5.dist-info/METADATA
pyfortracc-1.2.5.dist-info/WHEEL
pyfortracc-1.2.5.dist-info/top_level.txt
pyfortracc-1.2.5.dist-info/RECORD
