Metadata-Version: 2.4
Name: pyfortracc
Version: 1.2.5
Summary: A Python package for track and forecasting configurable clusters.
Home-page: https://github.com/fortracc/pyfortracc
Author: Helvecio B. L. Neto, Alan J. P. Calheiros
Author-email: fortracc.project@inpe.br
License: LICENSE
Classifier: Programming Language :: Python
Classifier: Development Status :: 5 - Production/Stable
Classifier: Operating System :: OS Independent
Classifier: Programming Language :: Python :: 3.10
Classifier: Programming Language :: Python :: 3.11
Classifier: Programming Language :: Python :: 3.12
Classifier: Topic :: Scientific/Engineering :: Hydrology
License-File: LICENSE
Requires-Dist: rasterio==1.4.3
Requires-Dist: geopandas==1.1.1
Requires-Dist: opencv-python-headless==4.11.0.86
Requires-Dist: xarray==2025.6.1
Requires-Dist: scipy==1.16.0
Requires-Dist: scikit-learn==1.6.1
Requires-Dist: pyarrow==19.0.1
Requires-Dist: duckdb==1.3.1
Requires-Dist: netCDF4==1.7.2
Requires-Dist: cartopy==0.24.0
Requires-Dist: shapelysmooth==0.2.1
Requires-Dist: tqdm==4.67.1
Requires-Dist: ipython==7.34.0
Requires-Dist: psutil==5.9.5
Requires-Dist: requests==2.32.4
Requires-Dist: gdown==5.2.0
Requires-Dist: geocube==0.7.1
Requires-Dist: rasterstats==0.20.0
Dynamic: author
Dynamic: author-email
Dynamic: classifier
Dynamic: description
Dynamic: description-content-type
Dynamic: home-page
Dynamic: license
Dynamic: license-file
Dynamic: requires-dist
Dynamic: summary
